{
  "$schema": "https://raw.githubusercontent.com/earendil-works/pi/main/packages/coding-agent/src/modes/interactive/theme/theme-schema.json",
  "name": "graphite-ui",
  "vars": {
    "bg": "#111111",
    "surface": "#181818",
    "surfaceAlt": "#242424",
    "surfaceRaised": "#2a2a2a",
    "selected": "#2a2a2a",
    "border": "#3a3a3a",
    "borderMuted": "#2b2b2b",
    "text": "#e2e2e2",
    "muted": "#a0a0a0",
    "dim": "#6f6f6f",
    "accent": "#cfcfcf",
    "bright": "#f0f0f0",
    "soft": "#b8b8b8",
    "success": "#9af08f",
    "error": "#ff7b82"
  },
  "colors": {
    "accent": "accent",
    "border": "border",
    "borderAccent": "accent",
    "borderMuted": "borderMuted",
    "success": "success",
    "error": "error",
    "warning": "soft",
    "muted": "muted",
    "dim": "dim",
    "text": "text",
    "thinkingText": "muted",

    "selectedBg": "selected",
    "userMessageBg": "#2d2d2d",
    "userMessageText": "bright",
    "customMessageBg": "surfaceRaised",
    "customMessageText": "text",
    "customMessageLabel": "accent",
    "toolPendingBg": "#202020",
    "toolSuccessBg": "#202020",
    "toolErrorBg": "#202020",
    "toolTitle": "bright",
    "toolOutput": "text",

    "mdHeading": "bright",
    "mdLink": "accent",
    "mdLinkUrl": "dim",
    "mdCode": "bright",
    "mdCodeBlock": "text",
    "mdCodeBlockBorder": "border",
    "mdQuote": "muted",
    "mdQuoteBorder": "borderMuted",
    "mdHr": "borderMuted",
    "mdListBullet": "accent",

    "toolDiffAdded": "success",
    "toolDiffRemoved": "error",
    "toolDiffContext": "muted",

    "syntaxComment": "dim",
    "syntaxKeyword": "bright",
    "syntaxFunction": "accent",
    "syntaxVariable": "text",
    "syntaxString": "soft",
    "syntaxNumber": "soft",
    "syntaxType": "accent",
    "syntaxOperator": "muted",
    "syntaxPunctuation": "muted",

    "thinkingOff": "borderMuted",
    "thinkingMinimal": "dim",
    "thinkingLow": "muted",
    "thinkingMedium": "soft",
    "thinkingHigh": "accent",
    "thinkingXhigh": "bright",

    "bashMode": "bright"
  },
  "export": {
    "pageBg": "#111111",
    "cardBg": "#181818",
    "infoBg": "#222222"
  }
}
