{
  "$schema": "https://raw.githubusercontent.com/earendil-works/pi/main/packages/coding-agent/src/modes/interactive/theme/theme-schema.json",
  "name": "grayscale-v1",
  "vars": {
    "bg": "#101010",
    "surface": "#1b1b1b",
    "elevated": "#2a2a2a",
    "highlight": "#3a3a3a",
    "border": "#343434",
    "borderStrong": "#5a5a5a",
    "muted": "#747474",
    "dim": "#a0a0a0",
    "text": "#c8c8c8",
    "green": "#00ff00",
    "red": "#ff0000"
  },
  "colors": {
    "accent": "dim",
    "border": "border",
    "borderAccent": "borderStrong",
    "borderMuted": "elevated",
    "success": "green",
    "error": "red",
    "warning": "dim",
    "muted": "muted",
    "dim": "dim",
    "text": "text",
    "thinkingText": "muted",
    "selectedBg": "highlight",
    "userMessageBg": "surface",
    "userMessageText": "text",
    "customMessageBg": "surface",
    "customMessageText": "text",
    "customMessageLabel": "dim",
    "toolPendingBg": "surface",
    "toolSuccessBg": "surface",
    "toolErrorBg": "surface",
    "toolTitle": "text",
    "toolOutput": "muted",
    "mdHeading": "text",
    "mdLink": "dim",
    "mdLinkUrl": "muted",
    "mdCode": "dim",
    "mdCodeBlock": "text",
    "mdCodeBlockBorder": "border",
    "mdQuote": "muted",
    "mdQuoteBorder": "border",
    "mdHr": "border",
    "mdListBullet": "dim",
    "toolDiffAdded": "green",
    "toolDiffRemoved": "red",
    "toolDiffContext": "muted",
    "syntaxComment": "muted",
    "syntaxKeyword": "text",
    "syntaxFunction": "dim",
    "syntaxVariable": "text",
    "syntaxString": "dim",
    "syntaxNumber": "text",
    "syntaxType": "dim",
    "syntaxOperator": "muted",
    "syntaxPunctuation": "muted",
    "thinkingOff": "bg",
    "thinkingMinimal": "surface",
    "thinkingLow": "elevated",
    "thinkingMedium": "borderStrong",
    "thinkingHigh": "dim",
    "thinkingXhigh": "text",
    "bashMode": "dim"
  },
  "export": {
    "pageBg": "#101010",
    "cardBg": "#1b1b1b",
    "infoBg": "#2a2a2a"
  }
}
